pywikilinks
