Metadata-Version: 1.1
Name: pywikilinks
Version: 0.0.2
Summary: Python package for downloading wiki-links corpus
Home-page: https://github.com/JonathanRaiman/pywikilinks
Author: Jonathan Raiman
Author-email: jraiman at mit dot edu
License: MIT
Download-URL: https://github.com/JonathanRaiman/pywikilinks
Keywords: Machine Learning,NLP
Platform: any
Classifier: Intended Audience :: Science/Research
Classifier: Operating System :: OS Independent
Classifier: Programming Language :: Python :: 3.3
Classifier: Topic :: Text Processing :: Linguistic
